cricket/__init__.py
cricket/compat.py
cricket/events.py
cricket/executor.py
cricket/main.py
cricket/model.py
cricket/pipes.py
cricket/view.py
cricket/django/__init__.py
cricket/django/__main__.py
cricket/django/discoverer.py
cricket/django/django_runtests.py
cricket/django/executor.py
cricket/django/model.py
cricket/unittest/__init__.py
cricket/unittest/__main__.py
cricket/unittest/discoverer.py
cricket/unittest/executor.py
cricket/unittest/model.py
cricket-0.2.5.dist-info/DESCRIPTION.rst
cricket-0.2.5.dist-info/METADATA
cricket-0.2.5.dist-info/RECORD
cricket-0.2.5.dist-info/WHEEL
cricket-0.2.5.dist-info/entry_points.txt
cricket-0.2.5.dist-info/metadata.json
cricket-0.2.5.dist-info/pbr.json
cricket-0.2.5.dist-info/top_level.txt
tests/__init__.py
tests/test_models.py
tests/test_unit_integration.py
